fiabilipy/__init__.py
fiabilipy/component.py
fiabilipy/markov.py
fiabilipy/system.py
fiabilipy/test_markov.py
fiabilipy/test_system.py
fiabilipy/voter.py
fiabilipyg_CdRom1-2.8.1.dist-info/METADATA
fiabilipyg_CdRom1-2.8.1.dist-info/WHEEL
fiabilipyg_CdRom1-2.8.1.dist-info/top_level.txt
fiabilipyg_CdRom1-2.8.1.dist-info/RECORD
