Metadata-Version: 2.1
Name: fiabilipyg-CdRom1
Version: 2.8.1
Summary: fiabilipy with .draw
Home-page: http://fiabilipy.org
Author: chabotsi, crubier, cdrom1
Author-email: contact@fiabilipy.org
License: UNKNOWN
Platform: UNKNOWN
Classifier: Programming Language :: Python :: 2
Classifier: License :: OSI Approved :: GNU General Public License v2 or later (GPLv2+)
Classifier: Operating System :: OS Independent
Requires-Python: >=2.7
